jawiki_cleaner/__init__.py
jawiki_cleaner/break_line.py
jawiki_cleaner/clean_text.py
jawiki_cleaner/cli.py
jawiki_cleaner/process.py
jawiki_cleaner-0.1.5.dist-info/entry_points.txt
jawiki_cleaner-0.1.5.dist-info/WHEEL
jawiki_cleaner-0.1.5.dist-info/METADATA
jawiki_cleaner-0.1.5.dist-info/RECORD
