Metadata-Version: 2.1
Name: jawiki-cleaner
Version: 0.1.5
Summary: Japanese Wikipedia cleaner
Home-page: https://github.com/hpprc/jawiki-cleaner
Author: hppRC
Author-email: hpp.ricecake@gmail.com
Requires-Python: >=3.8,<4.0
Classifier: Programming Language :: Python :: 3
Classifier: Programming Language :: Python :: 3.8
Project-URL: Repository, https://github.com/hpprc/jawiki-cleaner
